pywharf_backends/file_system/__init__.py
pywharf_backends/file_system/impl.py
pywharf_core/__init__.py
pywharf_core/backend.py
pywharf_core/job.py
pywharf_core/server.py
pywharf_core/utils.py
pywharf_core/web.py
pywharf_core/workflow.py
pywharf_testkit/__init__.py
pywharf_core-0.2.2.dist-info/entry_points.txt
pywharf_core-0.2.2.dist-info/LICENSE
pywharf_core-0.2.2.dist-info/WHEEL
pywharf_core-0.2.2.dist-info/METADATA
pywharf_core-0.2.2.dist-info/RECORD
